memento_client/__init__.py
memento_client/memento_client.py
memento_client/utils.py
memento_client-0.6.1.dist-info/DESCRIPTION.rst
memento_client-0.6.1.dist-info/METADATA
memento_client-0.6.1.dist-info/RECORD
memento_client-0.6.1.dist-info/WHEEL
memento_client-0.6.1.dist-info/metadata.json
memento_client-0.6.1.dist-info/top_level.txt
