Metadata-Version: 2.0
Name: memento-client
Version: 0.6.1
Summary: Official Python library for using the Memento Protocol
Home-page: https://github.com/mementoweb/py-memento-client
Author: Harihar Shankar, Shawn M. Jones, Herbert Van de Sompel
Author-email: prototeam@googlegroups.com
License: LICENSE.txt
Download-URL: https://github.com/mementoweb/py-memento-client
Keywords: memento http web archives
Platform: UNKNOWN
Classifier: Intended Audience :: Developers
Classifier: License :: OSI Approved :: BSD License
Classifier: Operating System :: OS Independent
Classifier: Topic :: Internet :: WWW/HTTP
Classifier: Topic :: Scientific/Engineering
Classifier: Topic :: Software Development :: Libraries :: Python Modules
Classifier: Topic :: Utilities
Classifier: Programming Language :: Python :: 2.7
Classifier: Programming Language :: Python :: 3.4
Classifier: Programming Language :: Python :: 3.5
Classifier: Programming Language :: Python :: 3.6
Requires-Dist: requests (>=2.7.0)
Provides-Extra: testing
Requires-Dist: pytest; extra == 'testing'
Provides-Extra: utils
Requires-Dist: lxml; extra == 'utils'
